02_sequential_basics/02_10_serial_to_parallel/02_10_serial_to_parallel.sv
//----------------------------------------------------------------------------
// Task
//----------------------------------------------------------------------------

module serial_to_parallel
# (
    parameter width = 8
)
(
    input                      clk,
    input                      rst,

    input                      serial_valid,
    input                      serial_data,

    output logic               parallel_valid,
    output logic [width - 1:0] parallel_data
);
    // Task:
    // Implement a module that converts serial data to the parallel multibit value.
    //
    // The module should accept one-bit values with valid interface in a serial manner.
    // After accumulating 'width' bits, the module should assert the parallel_valid
    // output and set the data.
    //
    // Note:
    // Check the waveform diagram in the README for better understanding.

    // $clog2 - tells how many bits are needed to represent values up to width - 1.
    logic [$clog2(width):0] bits_count;  // Counts how many bits received so far.
    logic [width - 1:0] shift_reg;       // Store the incoming bits.

    always_ff @(posedge clk or posedge rst) begin
        if (rst) begin
            bits_count     <= 0;
            shift_reg      <= 0;
            parallel_valid <= 0;
            parallel_data  <= 0;
        end else begin
            parallel_valid <= 0;

            if (serial_valid) begin
                shift_reg <= {shift_reg[width - 2:0], serial_data};
                bits_count <= bits_count + 1;

                if (bits_count == width - 1) begin
                    parallel_valid <= 1;
                    parallel_data  <= {shift_reg[width - 2:0], serial_data};
                    bits_count     <= 0;
                    shift_reg      <= 0;
                end
            end
        end
    end

endmodule

02_sequential_basics/02_10_serial_to_parallel/testbench.sv
`include "util.svh"

module testbench;

    // Clock and reset

    logic clk;

    initial
    begin
        clk = '0;

        forever
            # 500 clk = ~ clk;
    end

    logic rst;

    initial
    begin
        rst <= 'x;
        repeat (2) @ (posedge clk);
        rst <= '1;
        repeat (2) @ (posedge clk);
        rst <= '0;
    end

    //------------------------------------------------------------------------

    // Instantiation

    localparam width     = 8;

    localparam n_outputs = 100;
    localparam n_inputs  = n_outputs * width;

    // Minimum to count at least 1000 valid inputs
    localparam in_cnt_w  = $clog2(n_inputs + 1);
    // 8 times smaller than input
    localparam out_cnt_w = $clog2(n_outputs + 1);

    logic                   serial_valid;
    logic                   serial_data;

    wire                    parallel_valid;
    wire  [    width - 1:0] parallel_data;

    logic [ in_cnt_w - 1:0] in_vld_cnt;
    logic [out_cnt_w - 1:0] out_vld_cnt;

    serial_to_parallel  # (.width (width)) dut (.*);

    //------------------------------------------------------------------------

    // Monitor

    bit was_reset = 1'b0;

    logic queue [$];
    logic [width - 1:0] parallel_data_expected;

    always @ (posedge clk)
    begin
        if (rst)
        begin
            was_reset   <= 1'b1;
            out_vld_cnt <= '0;
            in_vld_cnt  <= '0;
            queue        = {};
        end
        else if (was_reset)
        begin
            if (serial_valid) begin
                in_vld_cnt <= in_vld_cnt + 1'b1;

                queue.push_back (serial_data);
            end

            if (parallel_valid)
            begin
                out_vld_cnt <= out_vld_cnt + 1'b1;

                if (queue.size () < width)
                begin
                    $display ("FAIL %s", `__FILE__);

                    $display ("++ TEST     => {%s, %s}",
                        `PD (queue.size ()), `PD (width));

                    $finish (1);
                end
                else
                begin
                    for (int i = 0; i < width; i ++)
                        // verilator lint_off BLKSEQ
                        parallel_data_expected [i] = queue.pop_front ();
                        // verilator lint_on BLKSEQ

                    if (parallel_data !== parallel_data_expected)
                    begin
                        $display ("FAIL %s", `__FILE__);

                        $display ("++ TEST     => {%s, %s}",
                            `PH (parallel_data), `PH (parallel_data_expected));

                        $finish (1);
                    end
                end
            end
        end
    end

    //------------------------------------------------------------------------

    // Stimulus generation

    int current_inputs;
    logic d_serial_valid, d_serial_data;

    initial
    begin
        `ifdef __ICARUS__
            // Uncomment the following line
            // to generate a VCD file and analyze it using GTKwave or Surfer

            // $dumpvars;
            $dumpfile("out.vcd");
            $dumpvars;
        `endif

        { serial_valid, serial_data } <= '0;

        @ (negedge rst);

        while (current_inputs != n_inputs)
        begin
            if (current_inputs <= 20)
            begin
                d_serial_valid = 1'b1;
                d_serial_data  = ~ serial_data;
            end
            else
            begin
                d_serial_valid = 1' ($urandom());
                d_serial_data  = 1' ($urandom());
            end

            current_inputs += 32' (d_serial_valid);

            { serial_valid, serial_data } <= { d_serial_valid, d_serial_data };

            @ (posedge clk);
        end

        // Stop driving and wait for output
        // We have to wait 2 cycles here: one to get an output from the module
        // and another one to wait for non-blocking assignment to out_vld_cnt
        serial_valid <= '0;
        @(posedge clk);
        @(posedge clk);

        if (in_cnt_w' (out_vld_cnt * width) !== in_vld_cnt) begin
            $display ("FAIL %s", `__FILE__);

            $display("++ TEST     => {%s != %s}", `PD(out_vld_cnt*width), `PD(in_vld_cnt));
            $display("++ EXPECTED => out_vld_cnt * width == in_vld_cnt");

            $finish (1);
        end

        $display ("PASS %s", `__FILE__);
        $finish;
    end

endmodule

02_sequential_basics/out.vcd
$date
	Sun Apr 13 17:09:52 2025
$end
$version
	Icarus Verilog
$end
$timescale
	1s
$end
$scope module testbench $end
$var wire 1 ! parallel_valid $end
$var wire 8 " parallel_data [7:0] $end
$var reg 1 # clk $end
$var reg 1 $ d_serial_data $end
$var reg 1 % d_serial_valid $end
$var reg 10 & in_vld_cnt [9:0] $end
$var reg 7 ' out_vld_cnt [6:0] $end
$var reg 8 ( parallel_data_expected [7:0] $end
$var reg 1 ) rst $end
$var reg 1 * serial_data $end
$var reg 1 + serial_valid $end
$var integer 32 , current_inputs [31:0] $end
$var reg 1 - was_reset $end
$scope module dut $end
$var wire 1 # clk $end
$var wire 1 ) rst $end
$var wire 1 * serial_data $end
$var wire 1 + serial_valid $end
$var reg 4 . bits_count [3:0] $end
$var reg 8 / parallel_data [7:0] $end
$var reg 1 ! parallel_valid $end
$var reg 8 0 shift_reg [7:0] $end
$upscope $end
$scope begin $ivl_for_loop0 $end
$var integer 32 1 i [31:0] $end
$upscope $end
$upscope $end
$enddefinitions $end
#0
$dumpvars
b0 1
bx 0
bx /
bx .
0-
b0 ,
0+
0*
x)
bx (
bx '
bx &
x%
x$
0#
bx "
x!
$end
#500
0!
1#
#1000
0#
#1500
b0 "
b0 /
b0 0
b0 .
1)
1#
#2000
0#
#2500
b0 &
b0 '
1-
1#
#3000
0#
#3500
1+
1*
b1 ,
1$
1%
0)
1#
#4000
0#
#4500
b1 .
b1 0
b1 &
0*
b10 ,
0$
1#
#5000
0#
#5500
b10 .
b10 0
1*
b10 &
b11 ,
1$
1#
#6000
0#
#6500
b11 .
b101 0
b11 &
0*
b100 ,
0$
1#
#7000
0#
#7500
b100 .
b1010 0
1*
b100 &
b101 ,
1$
1#
#8000
0#
#8500
b101 .
b10101 0
b101 &
0*
b110 ,
0$
1#
#9000
0#
#9500
b110 .
b101010 0
1*
b110 &
b111 ,
1$
1#
#10000
0#
#10500
b111 .
b1010101 0
b111 &
0*
b1000 ,
0$
1#
#11000
0#
#11500
b10101010 "
b10101010 /
1!
b0 .
b0 0
1*
b1000 &
b1001 ,
1$
1#
#12000
0#
#12500
b1 .
b1 0
0!
b1 '
b1001 &
0*
b1000 1
b1010101 (
b1010 ,
0$
1#
